flake8_rewriter/__init__.py
flake8_rewriter/rewriter.py
flake8_rewriter-1.2.0.dist-info/LICENSE
flake8_rewriter-1.2.0.dist-info/METADATA
flake8_rewriter-1.2.0.dist-info/WHEEL
flake8_rewriter-1.2.0.dist-info/entry_points.txt
flake8_rewriter-1.2.0.dist-info/top_level.txt
flake8_rewriter-1.2.0.dist-info/RECORD
