Metadata-Version: 2.1
Name: flake8-rewriter
Version: 1.2.0
Summary: Flake8 plugin that rewrites error codes.
Home-page: https://github.com/ILikePizza555/flake8-rewriter
Author: Isaac 'Izzy' Avram
Author-email: avrisaac555@gmail.com
License: MIT
Platform: UNKNOWN
Classifier: Framework :: Flake8
Classifier: Environment :: Console
Classifier: Intended Audience :: Developers
Classifier: License :: OSI Approved :: MIT License
Classifier: Programming Language :: Python
Classifier: Programming Language :: Python :: 2
Classifier: Programming Language :: Python :: 3
Classifier: Topic :: Software Development :: Libraries :: Python Modules
Classifier: Topic :: Software Development :: Quality Assurance
Requires-Dist: flake8 (>3.0.0)
